{"v":4,"entries":{"accordion--default":{"type":"story","id":"accordion--default","name":"Default","title":"Accordion","importPath":"./packages/components/src/core/Accordion/index.stories.tsx","tags":["story"]},"accordion--live-preview":{"type":"story","id":"accordion--live-preview","name":"Live Preview","title":"Accordion","importPath":"./packages/components/src/core/Accordion/index.stories.tsx","tags":["story"]},"accordion--test":{"type":"story","id":"accordion--test","name":"Test","title":"Accordion","importPath":"./packages/components/src/core/Accordion/index.stories.tsx","tags":["story"]},"alert-to-be-depreciated--default":{"type":"story","id":"alert-to-be-depreciated--default","name":"Default","title":"Alert - To Be Depreciated","importPath":"./packages/components/src/core/Alert/index.stories.tsx","tags":["story"]},"alert-to-be-depreciated--snackbar-alert":{"type":"story","id":"alert-to-be-depreciated--snackbar-alert","name":"Snackbar Alert","title":"Alert - To Be Depreciated","importPath":"./packages/components/src/core/Alert/index.stories.tsx","tags":["story"]},"alert-to-be-depreciated--test":{"type":"story","id":"alert-to-be-depreciated--test","name":"Test","title":"Alert - To Be Depreciated","importPath":"./packages/components/src/core/Alert/index.stories.tsx","tags":["story"]},"dropdowns-autocomplete--default":{"type":"story","id":"dropdowns-autocomplete--default","name":"Default","title":"Dropdowns/Autocomplete","importPath":"./packages/components/src/core/Autocomplete/index.stories.tsx","tags":["story"]},"dropdowns-autocomplete--single-column":{"type":"story","id":"dropdowns-autocomplete--single-column","name":"Single Column","title":"Dropdowns/Autocomplete","importPath":"./packages/components/src/core/Autocomplete/index.stories.tsx","tags":["story"]},"dropdowns-autocomplete--multi-column":{"type":"story","id":"dropdowns-autocomplete--multi-column","name":"Multi Column","title":"Dropdowns/Autocomplete","importPath":"./packages/components/src/core/Autocomplete/index.stories.tsx","tags":["story"]},"dropdowns-autocomplete--test":{"type":"story","id":"dropdowns-autocomplete--test","name":"Test","title":"Dropdowns/Autocomplete","importPath":"./packages/components/src/core/Autocomplete/index.stories.tsx","tags":["story"]},"banner--default":{"type":"story","id":"banner--default","name":"Default","title":"Banner","importPath":"./packages/components/src/core/Banner/index.stories.tsx","tags":["story"]},"banner--live-preview":{"type":"story","id":"banner--live-preview","name":"Live Preview","title":"Banner","importPath":"./packages/components/src/core/Banner/index.stories.tsx","tags":["story"]},"banner--test":{"type":"story","id":"banner--test","name":"Test","title":"Banner","importPath":"./packages/components/src/core/Banner/index.stories.tsx","tags":["story"]},"button--default":{"type":"story","id":"button--default","name":"Default","title":"Button","importPath":"./packages/components/src/core/Button/index.stories.tsx","tags":["story"]},"button--rounded-live-preview":{"type":"story","id":"button--rounded-live-preview","name":"Rounded Live Preview","title":"Button","importPath":"./packages/components/src/core/Button/index.stories.tsx","tags":["story"]},"button--square-live-preview":{"type":"story","id":"button--square-live-preview","name":"Square Live Preview","title":"Button","importPath":"./packages/components/src/core/Button/index.stories.tsx","tags":["story"]},"button--minimal-live-preview":{"type":"story","id":"button--minimal-live-preview","name":"Minimal Live Preview","title":"Button","importPath":"./packages/components/src/core/Button/index.stories.tsx","tags":["story"]},"button--screenshot-test":{"type":"story","id":"button--screenshot-test","name":"Screenshot Test","title":"Button","importPath":"./packages/components/src/core/Button/index.stories.tsx","tags":["story"]},"button--test":{"type":"story","id":"button--test","name":"Test","title":"Button","importPath":"./packages/components/src/core/Button/index.stories.tsx","tags":["story"]},"buttondropdown--default":{"type":"story","id":"buttondropdown--default","name":"Default","title":"ButtonDropdown","importPath":"./packages/components/src/core/ButtonDropdown/index.stories.tsx","tags":["story"]},"buttondropdown--live-preview":{"type":"story","id":"buttondropdown--live-preview","name":"Live Preview","title":"ButtonDropdown","importPath":"./packages/components/src/core/ButtonDropdown/index.stories.tsx","tags":["story"]},"buttondropdown--test":{"type":"story","id":"buttondropdown--test","name":"Test","title":"ButtonDropdown","importPath":"./packages/components/src/core/ButtonDropdown/index.stories.tsx","tags":["story"]},"buttonicon--default":{"type":"story","id":"buttonicon--default","name":"Default","title":"ButtonIcon","importPath":"./packages/components/src/core/ButtonIcon/index.stories.tsx","tags":["story"]},"buttonicon--live-preview":{"type":"story","id":"buttonicon--live-preview","name":"Live Preview","title":"ButtonIcon","importPath":"./packages/components/src/core/ButtonIcon/index.stories.tsx","tags":["story"]},"buttonicon--screenshot-test":{"type":"story","id":"buttonicon--screenshot-test","name":"Screenshot Test","title":"ButtonIcon","importPath":"./packages/components/src/core/ButtonIcon/index.stories.tsx","tags":["story"]},"buttonicon--test":{"type":"story","id":"buttonicon--test","name":"Test","title":"ButtonIcon","importPath":"./packages/components/src/core/ButtonIcon/index.stories.tsx","tags":["story"]},"callout--default":{"type":"story","id":"callout--default","name":"Default","title":"Callout","importPath":"./packages/components/src/core/Callout/index.stories.tsx","tags":["story"]},"callout--live-preview":{"type":"story","id":"callout--live-preview","name":"Live Preview","title":"Callout","importPath":"./packages/components/src/core/Callout/index.stories.tsx","tags":["story"]},"table-cellbasic--default":{"type":"story","id":"table-cellbasic--default","name":"Default","title":"Table/CellBasic","importPath":"./packages/components/src/core/CellBasic/index.stories.tsx","tags":["story"]},"table-cellbasic--test":{"type":"story","id":"table-cellbasic--test","name":"Test","title":"Table/CellBasic","importPath":"./packages/components/src/core/CellBasic/index.stories.tsx","tags":["story"]},"table-cellcomponent--default":{"type":"story","id":"table-cellcomponent--default","name":"Default","title":"Table/CellComponent","importPath":"./packages/components/src/core/CellComponent/index.stories.tsx","tags":["story"]},"table-cellcomponent--test":{"type":"story","id":"table-cellcomponent--test","name":"Test","title":"Table/CellComponent","importPath":"./packages/components/src/core/CellComponent/index.stories.tsx","tags":["story"]},"table-cellheader--default":{"type":"story","id":"table-cellheader--default","name":"Default","title":"Table/CellHeader","importPath":"./packages/components/src/core/CellHeader/index.stories.tsx","tags":["story"]},"table-cellheader--test":{"type":"story","id":"table-cellheader--test","name":"Test","title":"Table/CellHeader","importPath":"./packages/components/src/core/CellHeader/index.stories.tsx","tags":["story"]},"chip-to-be-depreciated--medium-square-chip":{"type":"story","id":"chip-to-be-depreciated--medium-square-chip","name":"Medium Square Chip","title":"Chip - To Be Depreciated","importPath":"./packages/components/src/core/Chip/index.stories.tsx","tags":["story"]},"chip-to-be-depreciated--success":{"type":"story","id":"chip-to-be-depreciated--success","name":"Success","title":"Chip - To Be Depreciated","importPath":"./packages/components/src/core/Chip/index.stories.tsx","tags":["story"]},"chip-to-be-depreciated--error":{"type":"story","id":"chip-to-be-depreciated--error","name":"Error","title":"Chip - To Be Depreciated","importPath":"./packages/components/src/core/Chip/index.stories.tsx","tags":["story"]},"chip-to-be-depreciated--warning":{"type":"story","id":"chip-to-be-depreciated--warning","name":"Warning","title":"Chip - To Be Depreciated","importPath":"./packages/components/src/core/Chip/index.stories.tsx","tags":["story"]},"chip-to-be-depreciated--info":{"type":"story","id":"chip-to-be-depreciated--info","name":"Info","title":"Chip - To Be Depreciated","importPath":"./packages/components/src/core/Chip/index.stories.tsx","tags":["story"]},"chip-to-be-depreciated--pending":{"type":"story","id":"chip-to-be-depreciated--pending","name":"Pending","title":"Chip - To Be Depreciated","importPath":"./packages/components/src/core/Chip/index.stories.tsx","tags":["story"]},"chip-to-be-depreciated--beta":{"type":"story","id":"chip-to-be-depreciated--beta","name":"Beta","title":"Chip - To Be Depreciated","importPath":"./packages/components/src/core/Chip/index.stories.tsx","tags":["story"]},"complexfilter--default":{"type":"story","id":"complexfilter--default","name":"Default","title":"ComplexFilter","importPath":"./packages/components/src/core/ComplexFilter/index.stories.tsx","tags":["story"]},"complexfilter--live-preview":{"type":"story","id":"complexfilter--live-preview","name":"Live Preview","title":"ComplexFilter","importPath":"./packages/components/src/core/ComplexFilter/index.stories.tsx","tags":["story"]},"complexfilter--test":{"type":"story","id":"complexfilter--test","name":"Test","title":"ComplexFilter","importPath":"./packages/components/src/core/ComplexFilter/index.stories.tsx","tags":["story"]},"dialog--default":{"type":"story","id":"dialog--default","name":"Default","title":"Dialog","importPath":"./packages/components/src/core/Dialog/index.stories.tsx","tags":["story"]},"dialog--live-preview":{"type":"story","id":"dialog--live-preview","name":"Live Preview","title":"Dialog","importPath":"./packages/components/src/core/Dialog/index.stories.tsx","tags":["story"]},"dialog--test":{"type":"story","id":"dialog--test","name":"Test","title":"Dialog","importPath":"./packages/components/src/core/Dialog/index.stories.tsx","tags":["story"]},"dialog--test-no-title-on-close":{"type":"story","id":"dialog--test-no-title-on-close","name":"Test No Title On Close","title":"Dialog","importPath":"./packages/components/src/core/Dialog/index.stories.tsx","tags":["story"]},"dialog--test-button-position-left":{"type":"story","id":"dialog--test-button-position-left","name":"Test Button Position Left","title":"Dialog","importPath":"./packages/components/src/core/Dialog/index.stories.tsx","tags":["story"]},"dropdowns-dropdown--default":{"type":"story","id":"dropdowns-dropdown--default","name":"Default","title":"Dropdowns/Dropdown","importPath":"./packages/components/src/core/Dropdown/index.stories.tsx","tags":["story"]},"dropdowns-dropdown--multi-column-with-buttons":{"type":"story","id":"dropdowns-dropdown--multi-column-with-buttons","name":"Multi Column With Buttons","title":"Dropdowns/Dropdown","importPath":"./packages/components/src/core/Dropdown/index.stories.tsx","tags":["story"]},"dropdowns-dropdown--loading-results-indicator":{"type":"story","id":"dropdowns-dropdown--loading-results-indicator","name":"Loading Results Indicator","title":"Dropdowns/Dropdown","importPath":"./packages/components/src/core/Dropdown/index.stories.tsx","tags":["story"]},"dropdowns-dropdown--inside-modal":{"type":"story","id":"dropdowns-dropdown--inside-modal","name":"Inside Modal","title":"Dropdowns/Dropdown","importPath":"./packages/components/src/core/Dropdown/index.stories.tsx","tags":["story"]},"dropdowns-dropdown--controlled-dropdown":{"type":"story","id":"dropdowns-dropdown--controlled-dropdown","name":"Controlled Dropdown","title":"Dropdowns/Dropdown","importPath":"./packages/components/src/core/Dropdown/index.stories.tsx","tags":["story"]},"dropdowns-dropdown--test":{"type":"story","id":"dropdowns-dropdown--test","name":"Test","title":"Dropdowns/Dropdown","importPath":"./packages/components/src/core/Dropdown/index.stories.tsx","tags":["story"]},"dropdowns-dropdownmenu--default":{"type":"story","id":"dropdowns-dropdownmenu--default","name":"Default","title":"Dropdowns/DropdownMenu","importPath":"./packages/components/src/core/DropdownMenu/index.stories.tsx","tags":["story"]},"dropdowns-dropdownmenu--multi-column":{"type":"story","id":"dropdowns-dropdownmenu--multi-column","name":"Multi Column","title":"Dropdowns/DropdownMenu","importPath":"./packages/components/src/core/DropdownMenu/index.stories.tsx","tags":["story"]},"dropdowns-dropdownmenu--live-preview":{"type":"story","id":"dropdowns-dropdownmenu--live-preview","name":"Live Preview","title":"Dropdowns/DropdownMenu","importPath":"./packages/components/src/core/DropdownMenu/index.stories.tsx","tags":["story"]},"dropdowns-dropdownmenu--screenshot-test":{"type":"story","id":"dropdowns-dropdownmenu--screenshot-test","name":"Screenshot Test","title":"Dropdowns/DropdownMenu","importPath":"./packages/components/src/core/DropdownMenu/index.stories.tsx","tags":["story"]},"dropdowns-dropdownmenu--test":{"type":"story","id":"dropdowns-dropdownmenu--test","name":"Test","title":"Dropdowns/DropdownMenu","importPath":"./packages/components/src/core/DropdownMenu/index.stories.tsx","tags":["story"]},"icon--default":{"type":"story","id":"icon--default","name":"Default","title":"Icon","importPath":"./packages/components/src/core/Icon/index.stories.tsx","tags":["story"]},"icon--icon-bank":{"type":"story","id":"icon--icon-bank","name":"Icon Bank","title":"Icon","importPath":"./packages/components/src/core/Icon/index.stories.tsx","tags":["story"]},"icon--test":{"type":"story","id":"icon--test","name":"Test","title":"Icon","importPath":"./packages/components/src/core/Icon/index.stories.tsx","tags":["story"]},"inputs-inputcheckbox--default":{"type":"story","id":"inputs-inputcheckbox--default","name":"Default","title":"Inputs/InputCheckbox","importPath":"./packages/components/src/core/InputCheckbox/index.stories.tsx","tags":["story"]},"inputs-inputcheckbox--live-preview":{"type":"story","id":"inputs-inputcheckbox--live-preview","name":"Live Preview","title":"Inputs/InputCheckbox","importPath":"./packages/components/src/core/InputCheckbox/index.stories.tsx","tags":["story"]},"inputs-inputcheckbox--test":{"type":"story","id":"inputs-inputcheckbox--test","name":"Test","title":"Inputs/InputCheckbox","importPath":"./packages/components/src/core/InputCheckbox/index.stories.tsx","tags":["story"]},"inputs-inputdropdown--default":{"type":"story","id":"inputs-inputdropdown--default","name":"Default","title":"Inputs/InputDropdown","importPath":"./packages/components/src/core/InputDropdown/index.stories.tsx","tags":["story"]},"inputs-inputdropdown--round-live-preview":{"type":"story","id":"inputs-inputdropdown--round-live-preview","name":"Round Live Preview","title":"Inputs/InputDropdown","importPath":"./packages/components/src/core/InputDropdown/index.stories.tsx","tags":["story"]},"inputs-inputdropdown--square-live-preview":{"type":"story","id":"inputs-inputdropdown--square-live-preview","name":"Square Live Preview","title":"Inputs/InputDropdown","importPath":"./packages/components/src/core/InputDropdown/index.stories.tsx","tags":["story"]},"inputs-inputdropdown--minimal-live-preview":{"type":"story","id":"inputs-inputdropdown--minimal-live-preview","name":"Minimal Live Preview","title":"Inputs/InputDropdown","importPath":"./packages/components/src/core/InputDropdown/index.stories.tsx","tags":["story"]},"inputs-inputdropdown--test":{"type":"story","id":"inputs-inputdropdown--test","name":"Test","title":"Inputs/InputDropdown","importPath":"./packages/components/src/core/InputDropdown/index.stories.tsx","tags":["story"]},"inputs-inputradio--default":{"type":"story","id":"inputs-inputradio--default","name":"Default","title":"Inputs/InputRadio","importPath":"./packages/components/src/core/InputRadio/index.stories.tsx","tags":["story"]},"inputs-inputradio--live-preview":{"type":"story","id":"inputs-inputradio--live-preview","name":"Live Preview","title":"Inputs/InputRadio","importPath":"./packages/components/src/core/InputRadio/index.stories.tsx","tags":["story"]},"inputs-inputradio--test":{"type":"story","id":"inputs-inputradio--test","name":"Test","title":"Inputs/InputRadio","importPath":"./packages/components/src/core/InputRadio/index.stories.tsx","tags":["story"]},"inputs-inputsearch--default":{"type":"story","id":"inputs-inputsearch--default","name":"Default","title":"Inputs/InputSearch","importPath":"./packages/components/src/core/InputSearch/index.stories.tsx","tags":["story"]},"inputs-inputsearch--round-live-preview":{"type":"story","id":"inputs-inputsearch--round-live-preview","name":"Round Live Preview","title":"Inputs/InputSearch","importPath":"./packages/components/src/core/InputSearch/index.stories.tsx","tags":["story"]},"inputs-inputsearch--square-live-preview":{"type":"story","id":"inputs-inputsearch--square-live-preview","name":"Square Live Preview","title":"Inputs/InputSearch","importPath":"./packages/components/src/core/InputSearch/index.stories.tsx","tags":["story"]},"inputs-inputsearch--test":{"type":"story","id":"inputs-inputsearch--test","name":"Test","title":"Inputs/InputSearch","importPath":"./packages/components/src/core/InputSearch/index.stories.tsx","tags":["story"]},"inputs-inputslider--default":{"type":"story","id":"inputs-inputslider--default","name":"Default","title":"Inputs/InputSlider","importPath":"./packages/components/src/core/InputSlider/index.stories.tsx","tags":["story"]},"inputs-inputslider--live-preview":{"type":"story","id":"inputs-inputslider--live-preview","name":"Live Preview","title":"Inputs/InputSlider","importPath":"./packages/components/src/core/InputSlider/index.stories.tsx","tags":["story"]},"inputs-inputslider--test":{"type":"story","id":"inputs-inputslider--test","name":"Test","title":"Inputs/InputSlider","importPath":"./packages/components/src/core/InputSlider/index.stories.tsx","tags":["story"]},"inputs-inputtext--default":{"type":"story","id":"inputs-inputtext--default","name":"Default","title":"Inputs/InputText","importPath":"./packages/components/src/core/InputText/index.stories.tsx","tags":["story"]},"inputs-inputtext--live-preview":{"type":"story","id":"inputs-inputtext--live-preview","name":"Live Preview","title":"Inputs/InputText","importPath":"./packages/components/src/core/InputText/index.stories.tsx","tags":["story"]},"inputs-inputtext--test":{"type":"story","id":"inputs-inputtext--test","name":"Test","title":"Inputs/InputText","importPath":"./packages/components/src/core/InputText/index.stories.tsx","tags":["story"]},"inputs-inputtoggle--default":{"type":"story","id":"inputs-inputtoggle--default","name":"Default","title":"Inputs/InputToggle","importPath":"./packages/components/src/core/InputToggle/index.stories.tsx","tags":["story"]},"inputs-inputtoggle--live-preview":{"type":"story","id":"inputs-inputtoggle--live-preview","name":"Live Preview","title":"Inputs/InputToggle","importPath":"./packages/components/src/core/InputToggle/index.stories.tsx","tags":["story"]},"inputs-inputtoggle--test":{"type":"story","id":"inputs-inputtoggle--test","name":"Test","title":"Inputs/InputToggle","importPath":"./packages/components/src/core/InputToggle/index.stories.tsx","tags":["story"]},"link--default":{"type":"story","id":"link--default","name":"Default","title":"Link","importPath":"./packages/components/src/core/Link/index.stories.tsx","tags":["story"]},"link--live-preview":{"type":"story","id":"link--live-preview","name":"Live Preview","title":"Link","importPath":"./packages/components/src/core/Link/index.stories.tsx","tags":["story"]},"link--screenshot-test":{"type":"story","id":"link--screenshot-test","name":"Screenshot Test","title":"Link","importPath":"./packages/components/src/core/Link/index.stories.tsx","tags":["story"]},"list--default":{"type":"story","id":"list--default","name":"Default","title":"List","importPath":"./packages/components/src/core/List/index.stories.tsx","tags":["story"]},"loadingindicator--default":{"type":"story","id":"loadingindicator--default","name":"Default","title":"LoadingIndicator","importPath":"./packages/components/src/core/LoadingIndicator/index.stories.tsx","tags":["story"]},"loadingindicator--custom-aria-label":{"type":"story","id":"loadingindicator--custom-aria-label","name":"Custom Aria Label","title":"LoadingIndicator","importPath":"./packages/components/src/core/LoadingIndicator/index.stories.tsx","tags":["story"]},"loadingindicator--live-preview":{"type":"story","id":"loadingindicator--live-preview","name":"Live Preview","title":"LoadingIndicator","importPath":"./packages/components/src/core/LoadingIndicator/index.stories.tsx","tags":["story"]},"loadingindicator--test":{"type":"story","id":"loadingindicator--test","name":"Test","title":"LoadingIndicator","importPath":"./packages/components/src/core/LoadingIndicator/index.stories.tsx","tags":["story"]},"dropdowns-menu--default":{"type":"story","id":"dropdowns-menu--default","name":"Default","title":"Dropdowns/Menu","importPath":"./packages/components/src/core/Menu/index.stories.tsx","tags":["story"]},"dropdowns-menu--custom-placement":{"type":"story","id":"dropdowns-menu--custom-placement","name":"Custom Placement","title":"Dropdowns/Menu","importPath":"./packages/components/src/core/Menu/index.stories.tsx","tags":["story"]},"dropdowns-menuitem--default":{"type":"story","id":"dropdowns-menuitem--default","name":"Default","title":"Dropdowns/MenuItem","importPath":"./packages/components/src/core/MenuItem/index.stories.tsx","tags":["story"]},"dropdowns-menuitem--screenshot-test":{"type":"story","id":"dropdowns-menuitem--screenshot-test","name":"Screenshot Test","title":"Dropdowns/MenuItem","importPath":"./packages/components/src/core/MenuItem/index.stories.tsx","tags":["story"]},"dropdowns-menuitem--test":{"type":"story","id":"dropdowns-menuitem--test","name":"Test","title":"Dropdowns/MenuItem","importPath":"./packages/components/src/core/MenuItem/index.stories.tsx","tags":["story"]},"dropdowns-menuselect-to-be-depreciated--default":{"type":"story","id":"dropdowns-menuselect-to-be-depreciated--default","name":"Default","title":"Dropdowns/MenuSelect - To Be Depreciated","importPath":"./packages/components/src/core/MenuSelect/index.stories.tsx","tags":["story"]},"dropdowns-menuselect-to-be-depreciated--single-select-with-search":{"type":"story","id":"dropdowns-menuselect-to-be-depreciated--single-select-with-search","name":"Single Select With Search","title":"Dropdowns/MenuSelect - To Be Depreciated","importPath":"./packages/components/src/core/MenuSelect/index.stories.tsx","tags":["story"]},"dropdowns-menuselect-to-be-depreciated--multi-select":{"type":"story","id":"dropdowns-menuselect-to-be-depreciated--multi-select","name":"Multi Select","title":"Dropdowns/MenuSelect - To Be Depreciated","importPath":"./packages/components/src/core/MenuSelect/index.stories.tsx","tags":["story"]},"dropdowns-menuselect-to-be-depreciated--multi-select-with-search":{"type":"story","id":"dropdowns-menuselect-to-be-depreciated--multi-select-with-search","name":"Multi Select With Search","title":"Dropdowns/MenuSelect - To Be Depreciated","importPath":"./packages/components/src/core/MenuSelect/index.stories.tsx","tags":["story"]},"navigationjumpto--default":{"type":"story","id":"navigationjumpto--default","name":"Default","title":"NavigationJumpTo","importPath":"./packages/components/src/core/NavigationJumpTo/index.stories.tsx","tags":["story"]},"navigationjumpto--live-preview":{"type":"story","id":"navigationjumpto--live-preview","name":"Live Preview","title":"NavigationJumpTo","importPath":"./packages/components/src/core/NavigationJumpTo/index.stories.tsx","tags":["story"]},"navigationjumpto--test":{"type":"story","id":"navigationjumpto--test","name":"Test","title":"NavigationJumpTo","importPath":"./packages/components/src/core/NavigationJumpTo/index.stories.tsx","tags":["story"]},"notification--default":{"type":"story","id":"notification--default","name":"Default","title":"Notification","importPath":"./packages/components/src/core/Notification/index.stories.tsx","tags":["story"]},"notification--live-preview":{"type":"story","id":"notification--live-preview","name":"Live Preview","title":"Notification","importPath":"./packages/components/src/core/Notification/index.stories.tsx","tags":["story"]},"notification--screenshot-test":{"type":"story","id":"notification--screenshot-test","name":"Screenshot Test","title":"Notification","importPath":"./packages/components/src/core/Notification/index.stories.tsx","tags":["story"]},"notification--test":{"type":"story","id":"notification--test","name":"Test","title":"Notification","importPath":"./packages/components/src/core/Notification/index.stories.tsx","tags":["story"]},"table-pagination--default":{"type":"story","id":"table-pagination--default","name":"Default","title":"Table/Pagination","importPath":"./packages/components/src/core/Pagination/index.stories.tsx","tags":["story"]},"table-pagination--test":{"type":"story","id":"table-pagination--test","name":"Test","title":"Table/Pagination","importPath":"./packages/components/src/core/Pagination/index.stories.tsx","tags":["story"]},"segmentedcontrol--default":{"type":"story","id":"segmentedcontrol--default","name":"Default","title":"SegmentedControl","importPath":"./packages/components/src/core/SegmentedControl/index.stories.tsx","tags":["story"]},"segmentedcontrol--live-preview":{"type":"story","id":"segmentedcontrol--live-preview","name":"Live Preview","title":"SegmentedControl","importPath":"./packages/components/src/core/SegmentedControl/index.stories.tsx","tags":["story"]},"segmentedcontrol--test":{"type":"story","id":"segmentedcontrol--test","name":"Test","title":"SegmentedControl","importPath":"./packages/components/src/core/SegmentedControl/index.stories.tsx","tags":["story"]},"table-table--default":{"type":"story","id":"table-table--default","name":"Default","title":"Table/Table","importPath":"./packages/components/src/core/Table/index.stories.tsx","tags":["story"]},"table-table--test":{"type":"story","id":"table-table--test","name":"Test","title":"Table/Table","importPath":"./packages/components/src/core/Table/index.stories.tsx","tags":["story"]},"table-tableheader--default":{"type":"story","id":"table-tableheader--default","name":"Default","title":"Table/TableHeader","importPath":"./packages/components/src/core/TableHeader/index.stories.tsx","tags":["story"]},"table-tableheader--test":{"type":"story","id":"table-tableheader--test","name":"Test","title":"Table/TableHeader","importPath":"./packages/components/src/core/TableHeader/index.stories.tsx","tags":["story"]},"table-tablerow--default":{"type":"story","id":"table-tablerow--default","name":"Default","title":"Table/TableRow","importPath":"./packages/components/src/core/TableRow/index.stories.tsx","tags":["story"]},"table-tablerow--test":{"type":"story","id":"table-tablerow--test","name":"Test","title":"Table/TableRow","importPath":"./packages/components/src/core/TableRow/index.stories.tsx","tags":["story"]},"tabs--default":{"type":"story","id":"tabs--default","name":"Default","title":"Tabs","importPath":"./packages/components/src/core/Tabs/index.stories.tsx","tags":["story"]},"tabs--live-preview":{"type":"story","id":"tabs--live-preview","name":"Live Preview","title":"Tabs","importPath":"./packages/components/src/core/Tabs/index.stories.tsx","tags":["story"]},"tabs--test":{"type":"story","id":"tabs--test","name":"Test","title":"Tabs","importPath":"./packages/components/src/core/Tabs/index.stories.tsx","tags":["story"]},"tag--default":{"type":"story","id":"tag--default","name":"Default","title":"Tag","importPath":"./packages/components/src/core/Tag/index.stories.tsx","tags":["story"]},"tag--live-preview":{"type":"story","id":"tag--live-preview","name":"Live Preview","title":"Tag","importPath":"./packages/components/src/core/Tag/index.stories.tsx","tags":["story"]},"tag--screenshot-test":{"type":"story","id":"tag--screenshot-test","name":"Screenshot Test","title":"Tag","importPath":"./packages/components/src/core/Tag/index.stories.tsx","tags":["story"]},"tag--gray-primary-screenshot-test":{"type":"story","id":"tag--gray-primary-screenshot-test","name":"Gray Primary Screenshot Test","title":"Tag","importPath":"./packages/components/src/core/Tag/index.stories.tsx","tags":["story"]},"tag--success-warning-screenshot-test":{"type":"story","id":"tag--success-warning-screenshot-test","name":"Success Warning Screenshot Test","title":"Tag","importPath":"./packages/components/src/core/Tag/index.stories.tsx","tags":["story"]},"tag--test":{"type":"story","id":"tag--test","name":"Test","title":"Tag","importPath":"./packages/components/src/core/Tag/index.stories.tsx","tags":["story"]},"tagfilter--default":{"type":"story","id":"tagfilter--default","name":"Default","title":"TagFilter","importPath":"./packages/components/src/core/TagFilter/index.stories.tsx","tags":["story"]},"tagfilter--live-preview":{"type":"story","id":"tagfilter--live-preview","name":"Live Preview","title":"TagFilter","importPath":"./packages/components/src/core/TagFilter/index.stories.tsx","tags":["story"]},"tagfilter--screenshot-test":{"type":"story","id":"tagfilter--screenshot-test","name":"Screenshot Test","title":"TagFilter","importPath":"./packages/components/src/core/TagFilter/index.stories.tsx","tags":["story"]},"tagfilter--test":{"type":"story","id":"tagfilter--test","name":"Test","title":"TagFilter","importPath":"./packages/components/src/core/TagFilter/index.stories.tsx","tags":["story"]},"tooltip--default":{"type":"story","id":"tooltip--default","name":"Default","title":"Tooltip","importPath":"./packages/components/src/core/Tooltip/index.stories.tsx","tags":["story"]},"tooltip--live-preview":{"type":"story","id":"tooltip--live-preview","name":"Live Preview","title":"Tooltip","importPath":"./packages/components/src/core/Tooltip/index.stories.tsx","tags":["story"]},"tooltip--placement-preview":{"type":"story","id":"tooltip--placement-preview","name":"Placement Preview","title":"Tooltip","importPath":"./packages/components/src/core/Tooltip/index.stories.tsx","tags":["story"]},"tooltip--screenshot-test":{"type":"story","id":"tooltip--screenshot-test","name":"Screenshot Test","title":"Tooltip","importPath":"./packages/components/src/core/Tooltip/index.stories.tsx","tags":["story"]},"tooltip--test":{"type":"story","id":"tooltip--test","name":"Test","title":"Tooltip","importPath":"./packages/components/src/core/Tooltip/index.stories.tsx","tags":["story"]},"tooltipcondensed--default":{"type":"story","id":"tooltipcondensed--default","name":"Default","title":"TooltipCondensed","importPath":"./packages/components/src/core/TooltipCondensed/index.stories.tsx","tags":["story"]},"tooltipcondensed--live-preview":{"type":"story","id":"tooltipcondensed--live-preview","name":"Live Preview","title":"TooltipCondensed","importPath":"./packages/components/src/core/TooltipCondensed/index.stories.tsx","tags":["story"]},"tooltipcondensed--test":{"type":"story","id":"tooltipcondensed--test","name":"Test","title":"TooltipCondensed","importPath":"./packages/components/src/core/TooltipCondensed/index.stories.tsx","tags":["story"]},"tooltiptable--default":{"type":"story","id":"tooltiptable--default","name":"Default","title":"TooltipTable","importPath":"./packages/components/src/core/TooltipTable/index.stories.tsx","tags":["story"]},"tooltiptable--live-preview":{"type":"story","id":"tooltiptable--live-preview","name":"Live Preview","title":"TooltipTable","importPath":"./packages/components/src/core/TooltipTable/index.stories.tsx","tags":["story"]},"tooltiptable--test":{"type":"story","id":"tooltiptable--test","name":"Test","title":"TooltipTable","importPath":"./packages/components/src/core/TooltipTable/index.stories.tsx","tags":["story"]},"data-viz-heatmapchart--default":{"type":"story","id":"data-viz-heatmapchart--default","name":"Default","title":"Data Viz/HeatmapChart","importPath":"./packages/data-viz/src/core/HeatmapChart/index.stories.tsx","tags":["story"]},"data-viz-heatmapchart--heatmap-demo":{"type":"story","id":"data-viz-heatmapchart--heatmap-demo","name":"Heatmap Demo","title":"Data Viz/HeatmapChart","importPath":"./packages/data-viz/src/core/HeatmapChart/index.stories.tsx","tags":["story"]}}}
